bnm/__init__.py
bnm/bnm.py
bnm/constants.py
bnmapi_python-0.0.1.dist-info/LICENSE
bnmapi_python-0.0.1.dist-info/METADATA
bnmapi_python-0.0.1.dist-info/WHEEL
bnmapi_python-0.0.1.dist-info/top_level.txt
bnmapi_python-0.0.1.dist-info/RECORD
