Metadata-Version: 2.1
Name: bnmapi-python
Version: 0.0.1
Summary: Unofficial python wrapper for Bank Negara Malaysia OpenAPI
Author: JasonLing
Project-URL: Homepage, https://github.com/JasonLing95/bnmapi-python
Keywords: python,wrapper,api,bnm
Requires-Python: >=3.7
License-File: LICENSE
Requires-Dist: requests
